commonroad_ots/__init__.py
commonroad_ots/abstractions/__init__.py
commonroad_ots/abstractions/abstraction_level.py
commonroad_ots/abstractions/evaluation_execution.py
commonroad_ots/abstractions/frame_factors.py
commonroad_ots/abstractions/simulation_execution.py
commonroad_ots/abstractions/warm_up_estimator.py
commonroad_ots/calibration/__init__.py
commonroad_ots/calibration/calibration.py
commonroad_ots/conversion/__init__.py
commonroad_ots/conversion/default_speed_limit.py
commonroad_ots/conversion/gtus.py
commonroad_ots/conversion/lane_groups.py
commonroad_ots/conversion/lanes.py
commonroad_ots/conversion/main.py
commonroad_ots/conversion/retransfer.py
commonroad_ots/conversion/setup.py
commonroad_ots/conversion/trafficlights.py
commonroad_ots/conversion/trafficsigns.py
commonroad_ots/conversion/utility.py
commonroad_ots/evaluation/InfrastructureMetrics.py
commonroad_ots/evaluation/NDTW.py
commonroad_ots/evaluation/RMSE.py
commonroad_ots/evaluation/SpawnDelay.py
commonroad_ots/evaluation/__init__.py
commonroad_ots/evaluation/data_collector.py
commonroad_ots/evaluation/vehicle_state.py
commonroad_ots/map_matching/__init__.py
commonroad_ots/map_matching/map_matching.py
commonroad_ots/visualization/__init__.py
commonroad_ots/visualization/create_video.py
commonroad_ots/visualization/plots.py
commonroad_ots/visualization/visualization.py
commonroad_ots-2025.1.dist-info/LICENSE.txt
commonroad_ots-2025.1.dist-info/METADATA
commonroad_ots-2025.1.dist-info/WHEEL
commonroad_ots-2025.1.dist-info/RECORD
