Metadata-Version: 2.3
Name: commonroad-ots
Version: 2025.1
Summary: Coupling CommonRoad and OpenTrafficSim.
License: BSD-3-Clause
Author: Christoph Thees
Author-email: christoph.thees@tum.de
Requires-Python: >=3.10,<4.0
Classifier: License :: OSI Approved :: BSD License
Classifier: Programming Language :: Python :: 3
Classifier: Programming Language :: Python :: 3.10
Classifier: Programming Language :: Python :: 3.11
Classifier: Programming Language :: Python :: 3.12
Classifier: Programming Language :: Python :: 3.13
Requires-Dist: JPype1 (>=1.5.0,<2.0.0)
Requires-Dist: commonroad-io (>=2023.4)
Requires-Dist: dtaidistance (>=2.3.11,<3.0.0)
Requires-Dist: matplot2tikz (>=0.3.3,<0.4.0)
Requires-Dist: matplotlib (>=3.7.0,<4.0.0)
Requires-Dist: networkx (>=3.2.1,<4.0.0)
Requires-Dist: numpy (>=1.26.1) ; python_version < "3.13"
Requires-Dist: numpy (>=2.1.0) ; python_version >= "3.13"
Requires-Dist: opentrafficsim (==1.7.5)
Requires-Dist: pandas (>=2.2.1,<3.0.0)
Requires-Dist: pyperclip (>=1.8.2,<2.0.0)
Requires-Dist: scipy (>=1.12.0,<2.0.0)
Requires-Dist: shapely (>=2.0.3,<3.0.0)
